AssembleAI/Requests.py
AssembleAI/__init__.py
AssembleAI/Base/BaseRequest.py
AssembleAI/Base/Exceptions.py
AssembleAI/Base/__init__.py
AssembleAI-0.0.0.0.22.dist-info/METADATA
AssembleAI-0.0.0.0.22.dist-info/WHEEL
AssembleAI-0.0.0.0.22.dist-info/top_level.txt
AssembleAI-0.0.0.0.22.dist-info/RECORD
