Metadata-Version: 2.1
Name: AssembleAI
Version: 0.0.0.0.22
Summary: Assemble AI
Author: SigireddyBalasai
Author-email: sigireddybalasai@gmail.com
License: MIT
Classifier: Development Status :: 5 - Production/Stable
Classifier: Intended Audience :: Developers
Classifier: Topic :: Software Development :: Build Tools
Classifier: License :: OSI Approved :: MIT License
Classifier: Programming Language :: Python :: 3.8
Classifier: Programming Language :: Python :: 3.9
Classifier: Programming Language :: Python :: 3.10
Requires-Dist: aiohttp
Requires-Dist: asyncio
Requires-Dist: aiofiles
